<?xml version="1.0" encoding="UTF-8"?>
<STRUCT CODE="R1" NAME="실시간 현물 호가" ATTR="NO" COMPRESS="NO" ATTRENDPOS="NO" BLOCK="NO" ENCRYPT="NO" CERTIFICATE="NO"
	CLSVALUE1="0x01" CLSVALUE2="1">
    <!--
     CLSVALUE1 값 종류
     0x01:호가, 0x02:체결, 0x04:거래원(비트OR)
     
     CLSVALUE2 값 종류
     1:현물(Default)
     -->
	<BLOCK CODE="OutBlock" NAME="OutBlock" SEND="NO" OCCURS="NO">
		<FIELD CODE="ITEMCODE" NAME="종목코드" TYPE="CHAR" SIZE="9"/>
        <FIELD CODE="TIME" NAME="현재시각" TYPE="CHAR" SIZE="6"/>
		<FIELD CODE="MTCD" NAME="장구분" TYPE="CHAR" SIZE="1"/>
        
		<FIELD CODE="ASKP1" NAME="매도호가1" TYPE="INT_NET" SIZE="1"/>
		<FIELD CODE="BIDP1" NAME="매수호가1" TYPE="INT_NET" SIZE="1"/>
		<FIELD CODE="ASKQ1" NAME="매도호가잔량1" TYPE="INT_NET" SIZE="1"/>
		<FIELD CODE="BIDQ1" NAME="매수호가잔량1" TYPE="INT_NET" SIZE="1"/>
		<FIELD CODE="ASKQDIFF1" NAME="매도호가잔량증감1" TYPE="INT_NET" SIZE="1"/>
		<FIELD CODE="BIDQDIFF1" NAME="매수호가잔량증감1" TYPE="INT_NET" SIZE="1"/>
        
        <FIELD CODE="ASKP2" NAME="매도호가2" TYPE="INT_NET" SIZE="1"/>
		<FIELD CODE="BIDP2" NAME="매수호가2" TYPE="INT_NET" SIZE="1"/>
		<FIELD CODE="ASKQ2" NAME="매도호가잔량2" TYPE="INT_NET" SIZE="1"/>
		<FIELD CODE="BIDQ2" NAME="매수호가잔량2" TYPE="INT_NET" SIZE="1"/>
		<FIELD CODE="ASKQDIFF2" NAME="매도호가잔량증감2" TYPE="INT_NET" SIZE="1"/>
		<FIELD CODE="BIDQDIFF2" NAME="매수호가잔량증감2" TYPE="INT_NET" SIZE="1"/>
        
        <FIELD CODE="ASKP3" NAME="매도호가3" TYPE="INT_NET" SIZE="1"/>
		<FIELD CODE="BIDP3" NAME="매수호가3" TYPE="INT_NET" SIZE="1"/>
		<FIELD CODE="ASKQ3" NAME="매도호가잔량3" TYPE="INT_NET" SIZE="1"/>
		<FIELD CODE="BIDQ3" NAME="매수호가잔량3" TYPE="INT_NET" SIZE="1"/>
		<FIELD CODE="ASKQDIFF3" NAME="매도호가잔량증감3" TYPE="INT_NET" SIZE="1"/>
		<FIELD CODE="BIDQDIFF3" NAME="매수호가잔량증감3" TYPE="INT_NET" SIZE="1"/>
        
        <FIELD CODE="ASKP4" NAME="매도호가4" TYPE="INT_NET" SIZE="1"/>
		<FIELD CODE="BIDP4" NAME="매수호가4" TYPE="INT_NET" SIZE="1"/>
		<FIELD CODE="ASKQ4" NAME="매도호가잔량4" TYPE="INT_NET" SIZE="1"/>
		<FIELD CODE="BIDQ4" NAME="매수호가잔량4" TYPE="INT_NET" SIZE="1"/>
		<FIELD CODE="ASKQDIFF4" NAME="매도호가잔량증감4" TYPE="INT_NET" SIZE="1"/>
		<FIELD CODE="BIDQDIFF4" NAME="매수호가잔량증감4" TYPE="INT_NET" SIZE="1"/>
        
        <FIELD CODE="ASKP5" NAME="매도호가5" TYPE="INT_NET" SIZE="1"/>
		<FIELD CODE="BIDP5" NAME="매수호가5" TYPE="INT_NET" SIZE="1"/>
		<FIELD CODE="ASKQ5" NAME="매도호가잔량5" TYPE="INT_NET" SIZE="1"/>
		<FIELD CODE="BIDQ5" NAME="매수호가잔량5" TYPE="INT_NET" SIZE="1"/>
		<FIELD CODE="ASKQDIFF5" NAME="매도호가잔량증감5" TYPE="INT_NET" SIZE="1"/>
		<FIELD CODE="BIDQDIFF5" NAME="매수호가잔량증감5" TYPE="INT_NET" SIZE="1"/>
        
        <FIELD CODE="ASKP6" NAME="매도호가6" TYPE="INT_NET" SIZE="1"/>
		<FIELD CODE="BIDP6" NAME="매수호가6" TYPE="INT_NET" SIZE="1"/>
		<FIELD CODE="ASKQ6" NAME="매도호가잔량6" TYPE="INT_NET" SIZE="1"/>
		<FIELD CODE="BIDQ6" NAME="매수호가잔량6" TYPE="INT_NET" SIZE="1"/>
		<FIELD CODE="ASKQDIFF6" NAME="매도호가잔량증감6" TYPE="INT_NET" SIZE="1"/>
		<FIELD CODE="BIDQDIFF6" NAME="매수호가잔량증감6" TYPE="INT_NET" SIZE="1"/>
        
        <FIELD CODE="ASKP7" NAME="매도호가7" TYPE="INT_NET" SIZE="1"/>
		<FIELD CODE="BIDP7" NAME="매수호가7" TYPE="INT_NET" SIZE="1"/>
		<FIELD CODE="ASKQ7" NAME="매도호가잔량7" TYPE="INT_NET" SIZE="1"/>
		<FIELD CODE="BIDQ7" NAME="매수호가잔량7" TYPE="INT_NET" SIZE="1"/>
		<FIELD CODE="ASKQDIFF7" NAME="매도호가잔량증감7" TYPE="INT_NET" SIZE="1"/>
		<FIELD CODE="BIDQDIFF7" NAME="매수호가잔량증감7" TYPE="INT_NET" SIZE="1"/>
        
        <FIELD CODE="ASKP8" NAME="매도호가8" TYPE="INT_NET" SIZE="1"/>
		<FIELD CODE="BIDP8" NAME="매수호가8" TYPE="INT_NET" SIZE="1"/>
		<FIELD CODE="ASKQ8" NAME="매도호가잔량8" TYPE="INT_NET" SIZE="1"/>
		<FIELD CODE="BIDQ8" NAME="매수호가잔량8" TYPE="INT_NET" SIZE="1"/>
		<FIELD CODE="ASKQDIFF8" NAME="매도호가잔량증감8" TYPE="INT_NET" SIZE="1"/>
		<FIELD CODE="BIDQDIFF8" NAME="매수호가잔량증감8" TYPE="INT_NET" SIZE="1"/>
        
        <FIELD CODE="ASKP9" NAME="매도호가9" TYPE="INT_NET" SIZE="1"/>
		<FIELD CODE="BIDP9" NAME="매수호가9" TYPE="INT_NET" SIZE="1"/>
		<FIELD CODE="ASKQ9" NAME="매도호가잔량9" TYPE="INT_NET" SIZE="1"/>
		<FIELD CODE="BIDQ9" NAME="매수호가잔량9" TYPE="INT_NET" SIZE="1"/>
		<FIELD CODE="ASKQDIFF9" NAME="매도호가잔량증감9" TYPE="INT_NET" SIZE="1"/>
		<FIELD CODE="BIDQDIFF9" NAME="매수호가잔량증감9" TYPE="INT_NET" SIZE="1"/>
        
        <FIELD CODE="ASKP10" NAME="매도호가10" TYPE="INT_NET" SIZE="1"/>
		<FIELD CODE="BIDP10" NAME="매수호가10" TYPE="INT_NET" SIZE="1"/>
		<FIELD CODE="ASKQ10" NAME="매도호가잔량10" TYPE="INT_NET" SIZE="1"/>
		<FIELD CODE="BIDQ10" NAME="매수호가잔량10" TYPE="INT_NET" SIZE="1"/>
		<FIELD CODE="ASKQDIFF10" NAME="매도호가잔량증감10" TYPE="INT_NET" SIZE="1"/>
		<FIELD CODE="BIDQDIFF10" NAME="매수호가잔량증감10" TYPE="INT_NET" SIZE="1"/>
        
		<FIELD CODE="T_ASKQ" NAME="총매도호가잔량" TYPE="INT_NET" SIZE="1"/>
		<FIELD CODE="T_BIDQ" NAME="총매수호가잔량" TYPE="INT_NET" SIZE="1"/>
		<FIELD CODE="T_ASKQDIFF" NAME="총매도호가잔량증감" TYPE="INT_NET" SIZE="1"/>
		<FIELD CODE="T_BIDQDIFF" NAME="총매수호가잔량증감" TYPE="INT_NET" SIZE="1"/>
            
        <FIELD CODE="ESTP" NAME="예상체결가" TYPE="INT_NET" SIZE="1"/>
        <FIELD CODE="ESTQ" NAME="예상체결수량" TYPE="INT_NET" SIZE="1"/>
        <FIELD CODE="GVOL" NAME="누적체결수량" TYPE="INT_NET" SIZE="1"/>
	</BLOCK>
</STRUCT>


